sds011/__init__.py
py_sds011-0.9.dist-info/LICENSE
py_sds011-0.9.dist-info/METADATA
py_sds011-0.9.dist-info/WHEEL
py_sds011-0.9.dist-info/top_level.txt
py_sds011-0.9.dist-info/RECORD
